{
  "pageId": "how-it-works",
  "updatedAt": "2026-04-02T22:33:15.244Z",
  "seo": {
    "en": {
      "title": "How It Works — Our Process | Madeira Property Concierge",
      "description": "From 30-minute diagnostic call to monthly operations in 30 days. See our founder-led onboarding — property audit, systems setup, and SLA-driven support.",
      "ogTitle": "From Diagnostic Call to Monthly Operations in 30 Days",
      "ogDescription": "See our founder-led onboarding process for Madeira property owners — property audit, systems setup, 4-hour SLA, and transparent monthly reporting.",
      "ogImage": "/images/madeira/green-ridges.webp",
      "canonical": "/en/how-it-works"
    },
    "pt": {
      "title": "Como Funciona — O Nosso Processo | Madeira Property Concierge",
      "description": "Da chamada de diagnostico a operacao mensal em 30 dias. Conheca o processo liderado pela fundadora — auditoria, setup de sistemas e suporte com SLA definido.",
      "ogTitle": "Da Chamada de Diagnostico a Operacao Mensal em 30 Dias",
      "ogDescription": "Conheca o nosso processo de onboarding para proprietarios na Madeira — auditoria do imovel, setup de sistemas, SLA de 4 horas e relatorios mensais.",
      "ogImage": "/images/madeira/green-ridges.webp",
      "canonical": "/pt/como-funciona"
    }
  },
  "texts": [
    {
      "id": "text:hero-eyebrow",
      "selector": "[data-cms-id=\"text:hero-eyebrow\"]",
      "kind": "inline",
      "value": {
        "en": "Operating Method",
        "pt": "Metodo Operacional"
      }
    },
    {
      "id": "text:hero-title",
      "selector": "[data-cms-id=\"text:hero-title\"]",
      "kind": "inline",
      "value": {
        "en": "A clear process for overseas owners.",
        "pt": "Um processo claro para proprietarios que gerem a distancia."
      }
    },
    {
      "id": "text:hero-subtitle",
      "selector": "[data-cms-id=\"text:hero-subtitle\"]",
      "kind": "inline",
      "value": {
        "en": "From first diagnostic to monthly rhythm, each phase is designed to reduce risk and improve predictability.",
        "pt": "Do primeiro diagnostico a rotina mensal, cada etapa foi desenhada para reduzir risco e aumentar previsibilidade."
      }
    },
    {
      "id": "text:step-1-title",
      "selector": "[data-cms-id=\"text:step-1-title\"]",
      "kind": "inline",
      "value": {
        "en": "Diagnostic Call",
        "pt": "Chamada de Diagnostico"
      }
    },
    {
      "id": "text:step-1-description",
      "selector": "[data-cms-id=\"text:step-1-description\"]",
      "kind": "inline",
      "value": {
        "en": "We start with a 30-minute call to map your property goals, risk profile, and operating model.",
        "pt": "Comecamos com uma chamada de 30 minutos para mapear objetivos, risco e modelo operacional do imovel."
      }
    },
    {
      "id": "text:step-2-title",
      "selector": "[data-cms-id=\"text:step-2-title\"]",
      "kind": "inline",
      "value": {
        "en": "Property & Risk Audit",
        "pt": "Auditoria de Imovel e Risco"
      }
    },
    {
      "id": "text:step-2-description",
      "selector": "[data-cms-id=\"text:step-2-description\"]",
      "kind": "inline",
      "value": {
        "en": "We assess property condition, compliance gaps, vendor/ utility setup, and service-tier fit.",
        "pt": "Avaliamos o estado do imóvel, lacunas de conformidade, configuração de fornecedores/utilidades e adequação do nível de serviço (Tier A, B, C ou D)."
      }
    },
    {
      "id": "text:step-3-title",
      "selector": "[data-cms-id=\"text:step-3-title\"]",
      "kind": "inline",
      "value": {
        "en": "Systems Setup",
        "pt": "Setup de Sistemas"
      }
    },
    {
      "id": "text:step-3-description",
      "selector": "[data-cms-id=\"text:step-3-description\"]",
      "kind": "inline",
      "value": {
        "en": "We activate workflows, communication templates, vendor standards, and guest/owner reporting routines.",
        "pt": "Ativamos fluxos operacionais, templates de comunicacao, padroes de fornecedores e rotinas de reporte."
      }
    },
    {
      "id": "text:step-4-title",
      "selector": "[data-cms-id=\"text:step-4-title\"]",
      "kind": "inline",
      "value": {
        "en": "Monthly Operations",
        "pt": "Operacao Mensal"
      }
    },
    {
      "id": "text:step-4-description",
      "selector": "[data-cms-id=\"text:step-4-description\"]",
      "kind": "inline",
      "value": {
        "en": "You receive monthly reporting, maintenance logs, and SLA-driven support with one clear point of contact.",
        "pt": "Recebe relatorio mensal, log de manutencao e suporte por SLA com um unico ponto de contacto responsavel."
      }
    },
    {
      "id": "text:deliverables-title",
      "selector": "[data-cms-id=\"text:deliverables-title\"]",
      "kind": "inline",
      "value": {
        "en": "What you receive consistently",
        "pt": "Entregaveis continuos"
      }
    },
    {
      "id": "text:deliverable-1",
      "selector": "[data-cms-id=\"text:deliverable-1\"]",
      "kind": "inline",
      "value": {
        "en": "Monthly owner report with occupancy, revenue, costs, and maintenance",
        "pt": "Relatorio mensal com ocupacao, receita, despesas e manutencao"
      }
    },
    {
      "id": "text:deliverable-3",
      "selector": "[data-cms-id=\"text:deliverable-3\"]",
      "kind": "inline",
      "value": {
        "en": "Maintenance and issue log with clear next actions",
        "pt": "Registo de ocorrencias e proximos passos com responsaveis definidos"
      }
    },
    {
      "id": "text:deliverable-4",
      "selector": "[data-cms-id=\"text:deliverable-4\"]",
      "kind": "inline",
      "value": {
        "en": "SLA targets: owner response within 4 business hours; guest emergencies within 30 mins",
        "pt": "SLA: resposta ao proprietario em ate 4h uteis; emergencias de hospedes em ate 30 minutos"
      }
    },
    {
      "id": "text:deliverable-5",
      "selector": "[data-cms-id=\"text:deliverable-5\"]",
      "kind": "inline",
      "value": {
        "en": "Single WhatsApp contact plus updates on critical decisions",
        "pt": "Comunicacao unica via WhatsApp e atualizacoes em decisoes criticas"
      }
    },
    {
      "id": "text:media-caption",
      "selector": "[data-cms-id=\"text:media-caption\"]",
      "kind": "inline",
      "value": {
        "en": "Operational Visibility",
        "pt": "Visibilidade Operacional"
      }
    },
    {
      "id": "text:timeline-title",
      "selector": "[data-cms-id=\"text:timeline-title\"]",
      "kind": "inline",
      "value": {
        "en": "Your first 30 days (onboarding)",
        "pt": "Primeiros 30 dias (onboarding)"
      }
    },
    {
      "id": "text:timeline-range-1",
      "selector": "[data-cms-id=\"text:timeline-range-1\"]",
      "kind": "inline",
      "value": {
        "en": "Day 1-2",
        "pt": "Dia 1-2"
      }
    },
    {
      "id": "text:timeline-text-1",
      "selector": "[data-cms-id=\"text:timeline-text-1\"]",
      "kind": "inline",
      "value": {
        "en": "Diagnostic call and package fit.",
        "pt": "Chamada de diagnostico e definicao do pacote mais adequado."
      }
    },
    {
      "id": "text:timeline-range-2",
      "selector": "[data-cms-id=\"text:timeline-range-2\"]",
      "kind": "inline",
      "value": {
        "en": "Day 3-5",
        "pt": "Dia 3-5"
      }
    },
    {
      "id": "text:timeline-text-2",
      "selector": "[data-cms-id=\"text:timeline-text-2\"]",
      "kind": "inline",
      "value": {
        "en": "Property audit: condition, needs/goals, risk, compliance and priorities.",
        "pt": "Auditoria do imovel: condicao, necessidades/objetivos, riscos, conformidade e prioridades."
      }
    },
    {
      "id": "text:timeline-range-3",
      "selector": "[data-cms-id=\"text:timeline-range-3\"]",
      "kind": "inline",
      "value": {
        "en": "Day 6-10",
        "pt": "Dia 6-10"
      }
    },
    {
      "id": "text:timeline-text-3",
      "selector": "[data-cms-id=\"text:timeline-text-3\"]",
      "kind": "inline",
      "value": {
        "en": "Property audit: condition, risk, compliance, and priorities.",
        "pt": "Auditoria do imovel: condicao, riscos, conformidade e prioridades."
      }
    },
    {
      "id": "text:timeline-range-4",
      "selector": "[data-cms-id=\"text:timeline-range-4\"]",
      "kind": "inline",
      "value": {
        "en": "Day 11-20",
        "pt": "Dia 11-20"
      }
    },
    {
      "id": "text:timeline-text-4",
      "selector": "[data-cms-id=\"text:timeline-text-4\"]",
      "kind": "inline",
      "value": {
        "en": "Vendor activation, SOP setup, and communication templates.",
        "pt": "Ativacao de fornecedores, SOPs e templates de comunicacao."
      }
    },
    {
      "id": "text:timeline-range-5",
      "selector": "[data-cms-id=\"text:timeline-range-5\"]",
      "kind": "inline",
      "value": {
        "en": "Day 21-30",
        "pt": "Dia 21-30"
      }
    },
    {
      "id": "text:timeline-text-5",
      "selector": "[data-cms-id=\"text:timeline-text-5\"]",
      "kind": "inline",
      "value": {
        "en": "Go-live with first monthly report and maintenance log.",
        "pt": "Operacao ativa com primeiro relatorio mensal e log de manutencao."
      }
    },
    {
      "id": "text:cta-title",
      "selector": "[data-cms-id=\"text:cta-title\"]",
      "kind": "inline",
      "value": {
        "en": "Your property should run on a system, not on surprises.",
        "pt": "O seu imovel deve funcionar com sistema, nao com surpresas."
      }
    },
    {
      "id": "text:cta-body",
      "selector": "[data-cms-id=\"text:cta-body\"]",
      "kind": "inline",
      "value": {
        "en": "Start with a diagnostic call and we'll show you what the day-to-day looks like.",
        "pt": "Comece com uma chamada de diagnostico e mostramos como funciona o dia-a-dia."
      }
    }
  ],
  "links": [
    {
      "id": "link:primary-cta",
      "selector": "[data-cms-id=\"link:primary-cta\"]",
      "label": {
        "en": "Get Started",
        "pt": "Começar Agora"
      },
      "href": {
        "en": "/en/contact",
        "pt": "/pt/contacto"
      }
    },
    {
      "id": "link:secondary-cta",
      "selector": "[data-cms-id=\"link:secondary-cta\"]",
      "label": {
        "en": "Pricing",
        "pt": "Precos"
      },
      "href": {
        "en": "/en/pricing",
        "pt": "/pt/precos"
      }
    }
  ],
  "images": []
}
